{
  "last_flush": "2026-07-13T20:44:38.205565+05:30",
  "items": [
    {
      "company": "KVS Castings Ltd",
      "scrip": "544554",
      "title": "KVS Castings Ltdhas informed BSE that the meeting of the Board of Directors of the Company is scheduled on 17/07/2026 ,inter alia, to consider and approve 1 To consider and approve the ....",
      "pdf": "https://www.bseindia.com/xml-data/corpfiling/AttachLive/d42cb823-4049-4e10-a715-0482cff6b70a.pdf"
    },
    {
      "company": "Innocorp Ltd",
      "scrip": "531929",
      "title": "Annual Report",
      "pdf": "https://www.bseindia.com/xml-data/corpfiling/AttachLive/ec99f6bf-d609-4a7d-bd64-dac682a07666.pdf"
    },
    {
      "company": "Sheela Foam Ltd",
      "scrip": "540203",
      "title": "Updated Annual Retport",
      "pdf": "https://www.bseindia.com/xml-data/corpfiling/AttachLive/82807885-cfaa-4651-9bdd-ba84035d567c.pdf"
    },
    {
      "company": "Palash Securities Ltd",
      "scrip": "540648",
      "title": "Pursuant to Regulation 34(1) of the SEBI (Listing Obligations and Disclosure Requirements) Regulations, 2015, ('Listing Regulations'), we enclose herewith a copy of the Annual Report including ....",
      "pdf": "https://www.bseindia.com/xml-data/corpfiling/AttachLive/e81cc90b-f848-406e-b691-de7b5ba18fa2.pdf"
    }
  ]
}
